aliyunsdkelasticsearch/__init__.py
aliyunsdkelasticsearch/endpoint.py
aliyunsdkelasticsearch/request/__init__.py
aliyunsdkelasticsearch/request/v20170613/ActivateZonesRequest.py
aliyunsdkelasticsearch/request/v20170613/AddConnectableClusterRequest.py
aliyunsdkelasticsearch/request/v20170613/AddSnapshotRepoRequest.py
aliyunsdkelasticsearch/request/v20170613/CancelDeletionRequest.py
aliyunsdkelasticsearch/request/v20170613/CancelLogstashDeletionRequest.py
aliyunsdkelasticsearch/request/v20170613/CancelTaskRequest.py
aliyunsdkelasticsearch/request/v20170613/CapacityPlanRequest.py
aliyunsdkelasticsearch/request/v20170613/CloseDiagnosisRequest.py
aliyunsdkelasticsearch/request/v20170613/CloseHttpsRequest.py
aliyunsdkelasticsearch/request/v20170613/CloseManagedIndexRequest.py
aliyunsdkelasticsearch/request/v20170613/CreateCollectorRequest.py
aliyunsdkelasticsearch/request/v20170613/CreateComponentIndexRequest.py
aliyunsdkelasticsearch/request/v20170613/CreateDataStreamRequest.py
aliyunsdkelasticsearch/request/v20170613/CreateILMPolicyRequest.py
aliyunsdkelasticsearch/request/v20170613/CreateIndexTemplateRequest.py
aliyunsdkelasticsearch/request/v20170613/CreateInstanceRequest.py
aliyunsdkelasticsearch/request/v20170613/CreateLogstashRequest.py
aliyunsdkelasticsearch/request/v20170613/CreatePipelinesRequest.py
aliyunsdkelasticsearch/request/v20170613/CreateSnapshotRequest.py
aliyunsdkelasticsearch/request/v20170613/CreateVpcEndpointRequest.py
aliyunsdkelasticsearch/request/v20170613/DeactivateZonesRequest.py
aliyunsdkelasticsearch/request/v20170613/DeleteCollectorRequest.py
aliyunsdkelasticsearch/request/v20170613/DeleteComponentIndexRequest.py
aliyunsdkelasticsearch/request/v20170613/DeleteConnectedClusterRequest.py
aliyunsdkelasticsearch/request/v20170613/DeleteDataStreamRequest.py
aliyunsdkelasticsearch/request/v20170613/DeleteDataTaskRequest.py
aliyunsdkelasticsearch/request/v20170613/DeleteDeprecatedTemplateRequest.py
aliyun_python_sdk_elasticsearch-3.1.2.dist-info/LICENSE
aliyun_python_sdk_elasticsearch-3.1.2.dist-info/METADATA
aliyun_python_sdk_elasticsearch-3.1.2.dist-info/WHEEL
aliyun_python_sdk_elasticsearch-3.1.2.dist-info/top_level.txt
aliyun_python_sdk_elasticsearch-3.1.2.dist-info/RECORD
