Metadata-Version: 2.1
Name: aliyun-python-sdk-elasticsearch
Version: 3.1.2
Summary: The elasticsearch module of Aliyun Python sdk.
Home-page: http://develop.aliyun.com/sdk/python
Author: Aliyun
Author-email: aliyun-developers-efficiency@list.alibaba-inc.com
License: Apache
Keywords: aliyun,sdk,elasticsearch
Platform: any
Classifier: Development Status :: 4 - Beta
Classifier: Intended Audience :: Developers
Classifier: License :: OSI Approved :: Apache Software License
Classifier: Programming Language :: Python
Classifier: Programming Language :: Python :: 2.6
Classifier: Programming Language :: Python :: 2.7
Classifier: Programming Language :: Python :: 3
Classifier: Programming Language :: Python :: 3.3
Classifier: Programming Language :: Python :: 3.4
Classifier: Programming Language :: Python :: 3.5
Classifier: Programming Language :: Python :: 3.6
Classifier: Topic :: Software Development
Requires-Dist: aliyun-python-sdk-core >=2.11.5
